childpages_card_grid/__init__.py
childpages_card_grid/content_manager.py
childpages_card_grid/page_parser.py
childpages_card_grid/plugin.py
childpages_card_grid/section_reader.py
mkdocs_childpages_card_grid_plugin-0.1.7.dist-info/LICENSE
mkdocs_childpages_card_grid_plugin-0.1.7.dist-info/METADATA
mkdocs_childpages_card_grid_plugin-0.1.7.dist-info/WHEEL
mkdocs_childpages_card_grid_plugin-0.1.7.dist-info/entry_points.txt
mkdocs_childpages_card_grid_plugin-0.1.7.dist-info/top_level.txt
mkdocs_childpages_card_grid_plugin-0.1.7.dist-info/RECORD
