Metadata-Version: 2.1
Name: mkdocs-childpages-card-grid-plugin
Version: 0.1.7
Summary: Create card grids with links to child pages on your MkDocs site
Home-page: https://github.com/faustool/mkdocs-childpages-card-grid-plugin
Author: Fausto Oliveira
License: Apache License, Version 2.0
Keywords: mkdocs,plugin,python,child-pages,card-grid
Classifier: Development Status :: 2 - Pre-Alpha
Classifier: Intended Audience :: Developers
Classifier: Intended Audience :: Information Technology
Classifier: License :: OSI Approved :: Apache Software License
Classifier: Programming Language :: Python :: 3
Requires-Python: >=3.7
License-File: LICENSE
Requires-Dist: mkdocs (>=1.4.0)
Requires-Dist: mkdocs-material (>=8.5.0)
